bumpymcbumpface.py
bumpymcbumpface-0.2.3.dist-info/LICENSE
bumpymcbumpface-0.2.3.dist-info/METADATA
bumpymcbumpface-0.2.3.dist-info/WHEEL
bumpymcbumpface-0.2.3.dist-info/entry_points.txt
bumpymcbumpface-0.2.3.dist-info/top_level.txt
bumpymcbumpface-0.2.3.dist-info/RECORD
