Metadata-Version: 2.1
Name: bumpymcbumpface
Version: 0.2.3
Summary: Version-bump, tag, push, deploy to PyPI
Home-page: https://github.com/cjrh/boatymcboatface
Author: Caleb Hattingh
Author-email: caleb.hattingh@gmail.com
License: UNKNOWN
Project-URL: Bug Reports, https://github.com/cjrh/bumpymcbumpface
Project-URL: Source, https://github.com/cjrh/bumpymcbumpface
Keywords: bump deploy version development
Platform: UNKNOWN
Classifier: Development Status :: 3 - Alpha
Classifier: Intended Audience :: Developers
Classifier: Topic :: Software Development :: Build Tools
Classifier: License :: OSI Approved :: GNU Affero General Public License v3 or later (AGPLv3+)
Classifier: Programming Language :: Python :: 2
Classifier: Programming Language :: Python :: 2.7
Classifier: Programming Language :: Python :: 3
Classifier: Programming Language :: Python :: 3.4
Classifier: Programming Language :: Python :: 3.5
Classifier: Programming Language :: Python :: 3.6
Classifier: Programming Language :: Python :: 3.7
Classifier: Programming Language :: Python :: 3.8
